reportlab_qr_code/__init__.py
reportlab_qr_code/__main__.py
reportlab_qr_code_generator-1.8.0.dist-info/LICENSE
reportlab_qr_code_generator-1.8.0.dist-info/METADATA
reportlab_qr_code_generator-1.8.0.dist-info/WHEEL
reportlab_qr_code_generator-1.8.0.dist-info/top_level.txt
reportlab_qr_code_generator-1.8.0.dist-info/RECORD
