Metadata-Version: 2.1
Name: reportlab_qr_code_generator
Version: 1.8.0
Summary: QR code plugin for reportlab and RML language
Author-email: Miroslav Bendík <miroslav.bendik@gmail.com>
License: MIT
Project-URL: homepage, https://github.com/mireq/reportlab-qr-code
Project-URL: documentation, https://github.com/mireq/reportlab-qr-code
Project-URL: repository, https://github.com/mireq/reportlab-qr-code
Project-URL: changelog, https://github.com/mireq/reportlab-qr-code/blob/master/CHANGELOG.md
Keywords: qr code,rml,reportlab
Classifier: Programming Language :: Python :: 3
Requires-Python: >=3.7
License-File: LICENSE
Requires-Dist: qrcode
Requires-Dist: six
Provides-Extra: dev
Requires-Dist: tox; extra == "dev"
Requires-Dist: pylint; extra == "dev"
Requires-Dist: pre-commit; extra == "dev"
Requires-Dist: bump2version; extra == "dev"
Requires-Dist: commitizen; extra == "dev"
